[{"seq": 2, "place": "Failand, North Somerset, UK", "source_page_id": "A_0197_L"}, {"seq": 3, "place": "Clifton Suspension Bridge, Bristol, UK", "source_page_id": "A_0197_R"}, {"seq": 4, "place": "SS Great Britain, Bristol, UK", "source_page_id": "A_0197_R"}, {"seq": 5, "place": "Bristol Cathedral, Bristol, UK", "source_page_id": "A_0197_R"}, {"seq": 6, "place": "Dockside Campsite, Bristol, UK", "source_page_id": "A_0198_L"}, {"seq": 7, "place": "The Deanery, Bristol, UK", "source_page_id": "A_0198_L"}]