[{"seq": 2, "place": "Woking, UK", "source_page_id": "B_0234_R"}, {"seq": 3, "place": "Folkestone (Eurotunnel)", "source_page_id": "B_0234_R"}, {"seq": 4, "place": "Noyelles-sur-Mer, France", "source_page_id": "B_0234_R"}, {"seq": 5, "place": "Caen, France", "source_page_id": "B_0235_L"}, {"seq": 6, "place": "Cherrueix, France", "source_page_id": "B_0235_L"}, {"seq": 7, "place": "Tr\u00e9guier, France", "source_page_id": "B_0236_L"}, {"seq": 8, "place": "Ploumanac'h, Perros-Guirec, France", "source_page_id": "B_0236_R"}, {"seq": 9, "place": "Sibiril, France", "source_page_id": "B_0237_R"}, {"seq": 10, "place": "Saint-Th\u00e9gonnec, France", "source_page_id": "B_0238_L"}, {"seq": 11, "place": "\u00c9tel, France", "source_page_id": "B_0238_R"}, {"seq": 12, "place": "Carnac, France", "source_page_id": "B_0241_L"}, {"seq": 13, "place": "Malestroit, France", "source_page_id": "B_0242_L"}, {"seq": 14, "place": "Brion, France", "source_page_id": "B_0243_L"}, {"seq": 15, "place": "Chambois, France", "source_page_id": "B_0243_L"}, {"seq": 16, "place": "M\u00e9morial de Montormel, France", "source_page_id": "B_0243_R"}, {"seq": 17, "place": "Saint-Paul, France", "source_page_id": "B_0244_L"}, {"seq": 18, "place": "Charleval, France", "source_page_id": "B_0244_L"}, {"seq": 19, "place": "Coquelles (Eurotunnel)", "source_page_id": "B_0244_L"}, {"seq": 20, "place": "Whittlesey, UK", "source_page_id": "B_0244_L"}]