[{"seq": 2, "place": "Wrest Park, Silsoe, Bedfordshire", "source_page_id": "B_0340_R"}, {"seq": 3, "place": "Berkhamsted, Hertfordshire", "source_page_id": "B_0340_R"}, {"seq": 4, "place": "Aylesbury, Buckinghamshire", "source_page_id": "B_0341_L"}, {"seq": 5, "place": "Chandler's Ford, Hampshire", "source_page_id": "B_0341_L"}, {"seq": 6, "place": "Swindon, Wiltshire", "source_page_id": "B_0341_L"}, {"seq": 7, "place": "Witney, Oxfordshire", "source_page_id": "B_0341_R"}, {"seq": 8, "place": "Finstock, Oxfordshire", "source_page_id": "B_0341_R"}, {"seq": 9, "place": "Edge Hill, Warwickshire", "source_page_id": "B_0341_R"}]