{
  "trip_id": "1994-france-picardy-champagne-burgundy-laon-troyes",
  "epigraph": {
    "quote": "We took a funicular up to the town, bought delicious patisserie + walked to the wrong church!",
    "source_page_id": "A_0131_L"
  },
  "per_stop": [
    {
      "seq": 2,
      "source_page_id": "A_0130_R",
      "quote": "Barry Guy got everyone to improvise, set off by his double bass. Very hot."
    },
    {
      "seq": 3,
      "source_page_id": "A_0130_R",
      "quote": "At the end of the trip we heard \"Will the parents of Charles Kirby please come to the Information desk on C Deck?\""
    },
    {
      "seq": 6,
      "source_page_id": "A_0131_R",
      "quote": "5 girls were playing ping pong with Peter. Thomas + William went to help + there was all-out chaos with the girls running off with the bats + ball."
    },
    {
      "seq": 7,
      "source_page_id": "A_0131_L",
      "quote": "We took a funicular up to the town, bought delicious patisserie + walked to the wrong church!"
    },
    {
      "seq": 8,
      "source_page_id": "A_0132_L",
      "quote": "It's a green, quiet campsite with a barn with ping pong + football. In the afternoon we went down to the river to paddle."
    },
    {
      "seq": 9,
      "source_page_id": "A_0132_R",
      "quote": "The cathedral is lovely, calm, uncluttered. Stained glass windows."
    },
    {
      "seq": 10,
      "source_page_id": "A_0132_R",
      "quote": "Charles is very brave with the cold water. Everyone took it in turns to ice down in the freezing water. White chalk billows up."
    },
    {
      "seq": 11,
      "source_page_id": "A_0134_R",
      "quote": "A dog came up while I sketched this in a driveway near Autun + ate half a very dead dead rabbit."
    },
    {
      "seq": 12,
      "source_page_id": "A_0135_R",
      "quote": "We drove on to St. Jean de Vaux, & camped in the middle of the Burgundy Vineyards."
    },
    {
      "seq": 13,
      "source_page_id": "A_0137_R",
      "quote": "William bumped his head for the first time because of his height on the tunnel ceiling."
    },
    {
      "seq": 14,
      "source_page_id": "A_0138_L",
      "quote": "We drove north + looked at a wood + plaster church at Ste. Marie-du-lac, a nice church with a minstrel's gallery."
    }
  ]
}
