{
  "trip_id": "2022-france-switzerland-vitry-le-francois-gray",
  "epigraph": {
    "quote": "We had a drink in the bar (Wi-Fi) for waiting for Charles to ring, but he didn't.",
    "source_page_id": "B_0366_L"
  },
  "per_stop": [
    {
      "seq": 2,
      "source_page_id": "B_0366_L",
      "quote": "We had a good supper at the Plough in our usual Kent campsite"
    },
    {
      "seq": 4,
      "source_page_id": "B_0366_L",
      "quote": "A Ventra walk before bed."
    },
    {
      "seq": 5,
      "source_page_id": "B_0366_L",
      "quote": "had lunch at the Brasserie overlooking the weir. A boat went down the lock."
    },
    {
      "seq": 6,
      "source_page_id": "B_0366_L",
      "quote": "5 villages make up a ski resort lovely small valley."
    },
    {
      "seq": 7,
      "source_page_id": "B_0366_R",
      "quote": "For 30 min we came downhill with both brakes on squeaking all the way down."
    },
    {
      "seq": 8,
      "source_page_id": "B_0367_L",
      "quote": "Glaciers. Through the Susten pass. Mad motorcyclists."
    },
    {
      "seq": 9,
      "source_page_id": "B_0367_L",
      "quote": "south through the St. Gotthard Tunnel. 17R long."
    },
    {
      "seq": 10,
      "source_page_id": "B_0367_L",
      "quote": "They don't have the parts that broke. (probably sold out to other people with busted awnings)"
    },
    {
      "seq": 11,
      "source_page_id": "B_0367_R",
      "quote": "We passed poplar plantations and rice paddy fields."
    },
    {
      "seq": 12,
      "source_page_id": "B_0370_L",
      "quote": "It still has 6 monks. Beautiful carvings, inlays, frescoes."
    },
    {
      "seq": 13,
      "source_page_id": "B_0371_R",
      "quote": "a lovely rural campsite downhill from the village"
    }
  ]
}
