{
 "trip_id": "2008-day-outings-hampton-lode-severn-valley",
 "title_guess": "Day outings: Hampton Lode / Severn Valley Park & Churchill Forge",
 "date_guess": "2008-05",
 "volume": "B",
 "spread_range": [
  "B_0135",
  "B_0135"
 ],
 "mixed_start": false,
 "mixed_end": false,
 "index_entry": null,
 "boundary_evidence": [],
 "sketch_images": [],
 "pages": [
  {
   "page_id": "B_0135_L",
   "no": null,
   "dates": [
    {
     "raw": "April 26th 2008",
     "iso": "2008-04-26"
    },
    {
     "raw": "Sunday May 11th",
     "iso": "2008-05-11"
    }
   ],
   "headings": [
    "Sunday May 11th"
   ],
   "places": [
    "Hampton Lode",
    "Severn Valley Park",
    "Alveley",
    "Churchhill Forge"
   ],
   "legibility": 0.88,
   "text": "April 26th 2008\n\n   We went for lunch to Hampton Lode in the autumn. Today we took Margaret + Helen out to the Severn Valley Park at Alveley, where we ate lunch in the van + then walked down with Tonic to see the new bridge.\n   On the way home we stopped at John Russell's house for Simon to fix his computer + Eve went to feed huln, while Simon drove home to feed the dog.\n\n__Sunday May 11th__\n   At 2.15. we picked up Margaret + Helen + drove to Churchhill Forge. It's one of the only watermills still going in the country. An overshot + an undershot mill, various hammers, belts, grease, friendly guides. Margaret sat up by the inlet water while we looked at the mill."
  },
  {
   "page_id": "B_0135_R",
   "no": 73,
   "dates": [
    {
     "raw": "1996",
     "iso": "1996"
    }
   ],
   "headings": [
    "CHURCHILL FORGE"
   ],
   "places": [
    "Churchill Forge"
   ],
   "captions": [
    "CHURCHILL FORGE"
   ],
   "legibility": 0.95,
   "text": "[Printed/illustrated postcard or leaflet glued in, showing six pen-and-ink drawings of watermill machinery with the text:] CHURCHILL FORGE [and] 1996"
  }
 ]
}