{
 "trip_id": "2022-scotland-crail-conta-s-wedding",
 "title_guess": "Scotland: Crail (Conta's wedding)",
 "date_guess": "2022-03",
 "volume": "B",
 "spread_range": [
  "B_0361",
  "B_0361"
 ],
 "mixed_start": false,
 "mixed_end": true,
 "index_entry": null,
 "boundary_evidence": [],
 "sketch_images": [],
 "pages": [
  {
   "page_id": "B_0361_L",
   "no": null,
   "dates": [
    {
     "raw": "Saturday",
     "iso": null
    },
    {
     "raw": "Sunday",
     "iso": null
    }
   ],
   "headings": [
    "Saturday",
    "Sunday"
   ],
   "places": [
    "Crail",
    "Cow Shed at Crail"
   ],
   "legibility": 0.82,
   "boundary_mixed": true,
   "text": "[Chorby?] Woods at about 8.25. for breakfast, on the road again at 8.55. We went on + on + will be getting to Crail about 4.15. Conta has rented a house where we are staying. She is organising a pre-wedding supper in a hall, to which we are bringing Welsh daffodils. The dinner all went very well. Conta had cooked delicious Lasagna, peas + chocdate Brownies. Claudia + Theo went to supper with their father, Joss + Wanda ate with us. We slept in Conta's house.\n\n__Saturday__\nAlas Conta woke up with a throbbing headache + bore throat + tested positive for Covid 19. The wedding was beautiful in the Cow Shed at Crail. There was an amusing MC. Theo played the [Piano?]. Joss told a poem. Over 200 at the wedding. Delicious beef cheek. We had to leave after the dancing started because of strobe lights. Alfie made a speech about how nice Conta is.\n\n__Sunday__\nWe chatted + then went to the brunch back in the Crushed. Louisa had baked a triple cake - lemon? vanilla, chocolate, ginger? The brunch was also super. We chatted to new friends + said Goodbye to all, including David + Maxine, who was 60 on the day."
  }
 ]
}